{
 "url": "https://www.nissan-stadium.jp/shinyoko-park/drone.php",
 "owner": "横浜市",
 "pref": "神奈川県",
 "etag": null,
 "last_modified": null,
 "digest": "a2476af41e9653fbb79b40ee931cc5dd2d0c485f32aeefa72a3fe53b8739ba47",
 "keywords": [
  "ドローン",
  "ラジコン",
  "無人航空機"
 ],
 "snippets": [
  "新横浜公園内でのドローン等の飛行について｜新横浜公園",
  "新横浜公園",
  "新横浜公園",
  "> 新横浜公園内でのドローン等の飛行について",
  "新横浜公園内でのドローン等の飛行について",
  "ドローン等の飛行については、平成27年に航空法が改正され、無人航空機（ドローン、ラジコン機等）の安全な飛行のためのガイドラインが示されております。",
  "この中で、場合により国土交通大臣の飛行の許可・承認が必要となることと合わせて、飛行させる場所の下に第三者がいると、操縦ミスなどで無人航空機が落下した際に大きな危害を及ぼすおそれがあるので、「学校、病院等の不特定多数の人が集まる場所の上空では飛行させない」旨の記載があります。",
  "当公園は、市内最大の運動公園であり、日産スタジアムをはじめとする運動施設や自由広場があることから、終日、多くの来園者が訪れます。",
  "このことから、当公園は、上記ガイドラインの記載にある「不特定多数の人が集まる場所」であると考えられますので、当公園では国土交通大臣の飛行許可・承認があった場合も、ドローン飛行による園内利用は原則としておことわりしております。",
  "全ての来園者に安全にご利用いただくために、皆さまのご理解をお願いいたします。"
 ],
 "checked": "2026-07-16"
}